zarr_particle_tools/__init__.py
zarr_particle_tools/subtomo_extract.py
zarr_particle_tools/subtomo_reconstruct.py
zarr_particle_tools/cli/__init__.py
zarr_particle_tools/cli/options.py
zarr_particle_tools/cli/types.py
zarr_particle_tools/core/backprojection.py
zarr_particle_tools/core/constants.py
zarr_particle_tools/core/ctf.py
zarr_particle_tools/core/data.py
zarr_particle_tools/core/dose.py
zarr_particle_tools/core/forwardprojection.py
zarr_particle_tools/core/helpers.py
zarr_particle_tools/core/mask.py
zarr_particle_tools/core/symmetry.py
zarr_particle_tools/core/symmetry_constants.py
zarr_particle_tools/generate/__init__.py
zarr_particle_tools/generate/cdp_cache.py
zarr_particle_tools/generate/cdp_generate_starfiles.py
zarr_particle_tools/generate/copick_generate_starfiles.py
zarr_particle_tools/pipeliner/__init__.py
zarr_particle_tools/pipeliner/subtomo_extract_pipeliner_job.py
zarr_particle_tools/pipeliner/subtomo_reconstruct_pipeliner_job.py
zarr_particle_tools/tools/__init__.py
zarr_particle_tools/tools/compare_mrcs.py
zarr_particle_tools-0.3.4.dist-info/METADATA
zarr_particle_tools-0.3.4.dist-info/WHEEL
zarr_particle_tools-0.3.4.dist-info/entry_points.txt
zarr_particle_tools-0.3.4.dist-info/licenses/LICENSE
zarr_particle_tools-0.3.4.dist-info/RECORD
