Metadata-Version: 2.4
Name: zarr-particle-tools
Version: 0.3.4
Summary: Subtomogram extraction from local files and the CryoET Data Portal.
Author: Daniel Ji, Utz Heinrich Ermel
License: MIT License
License-File: LICENSE
Keywords: cryo-et,cryoet,particle,subtomogram,tomography,zarr
Classifier: Development Status :: 4 - Beta
Classifier: License :: OSI Approved :: MIT License
Classifier: Programming Language :: Python
Classifier: Programming Language :: Python :: 3.10
Classifier: Programming Language :: Python :: 3.11
Classifier: Programming Language :: Python :: 3.12
Classifier: Programming Language :: Python :: 3.13
Classifier: Programming Language :: Python :: Implementation :: CPython
Requires-Python: >=3.10
Requires-Dist: click
Requires-Dist: copick
Requires-Dist: cryoet-alignment>=0.1.1
Requires-Dist: cryoet-data-portal
Requires-Dist: dask
Requires-Dist: mrcfile
Requires-Dist: numpy
Requires-Dist: pandas
Requires-Dist: rich
Requires-Dist: s3fs
Requires-Dist: scipy
Requires-Dist: starfile
Provides-Extra: dev
Requires-Dist: black>=25.1.0; extra == 'dev'
Requires-Dist: hatch-vcs>=0.4.0; extra == 'dev'
Requires-Dist: hatchling>=1.25.0; extra == 'dev'
Requires-Dist: matplotlib; extra == 'dev'
Requires-Dist: pre-commit>=4.2.0; extra == 'dev'
Requires-Dist: pytest; extra == 'dev'
Requires-Dist: pytest-xdist; extra == 'dev'
Requires-Dist: ruff>=0.12.0; extra == 'dev'
Requires-Dist: seaborn; extra == 'dev'
